{"classData":[{"comment":"/**\n * @class Neo.grid.header.Toolbar\n * @extends Neo.container.Toolbar\n */","meta":{"filename":"Toolbar.mjs","lineno":3,"columnno":0,"path":"/Users/Shared/github/neomjs/neomjs-realworld-example-app/node_modules/neo.mjs/src/grid/header","code":{}},"kind":"class","name":"Toolbar","augments":["Neo.container.Toolbar"],"memberof":"Neo.grid.header","longname":"Neo.grid.header.Toolbar","scope":"static","$longname":"Neo.grid.header.Toolbar","$kind":"class","id":1808,"neoClassName":"Neo.grid.header.Toolbar"},{"comment":"/**\n         * @member {String} className='Neo.grid.header.Toolbar'\n         * @protected\n         */","meta":{"filename":"Toolbar.mjs","lineno":13,"columnno":8,"path":"/Users/Shared/github/neomjs/neomjs-realworld-example-app/node_modules/neo.mjs/src/grid/header","code":{}},"kind":"member","name":"className","type":{"names":["String"]},"defaultvalue":"'Neo.grid.header.Toolbar'","access":"protected","longname":"className","scope":"global","$longname":"className","$kind":"property","id":1809,"neoClassName":"Neo.grid.header.Toolbar"},{"comment":"/**\n         * @member {String} ntype='grid-header-toolbar'\n         * @protected\n         */","meta":{"filename":"Toolbar.mjs","lineno":18,"columnno":8,"path":"/Users/Shared/github/neomjs/neomjs-realworld-example-app/node_modules/neo.mjs/src/grid/header","code":{}},"kind":"member","name":"ntype","type":{"names":["String"]},"defaultvalue":"'grid-header-toolbar'","access":"protected","longname":"ntype","scope":"global","$longname":"ntype","$kind":"property","id":1810,"neoClassName":"Neo.grid.header.Toolbar"},{"comment":"/**\n         * @member {Array} cls=['neo-grid-header-toolbar']\n         */","meta":{"filename":"Toolbar.mjs","lineno":22,"columnno":8,"path":"/Users/Shared/github/neomjs/neomjs-realworld-example-app/node_modules/neo.mjs/src/grid/header","code":{}},"kind":"member","name":"cls","type":{"names":["Array"]},"defaultvalue":"['neo-grid-header-toolbar']","longname":"cls","scope":"global","$longname":"cls","$kind":"property","id":1811,"neoClassName":"Neo.grid.header.Toolbar"},{"comment":"/**\n         * @member {String} _layout='base'\n         * @protected\n         */","meta":{"filename":"Toolbar.mjs","lineno":27,"columnno":8,"path":"/Users/Shared/github/neomjs/neomjs-realworld-example-app/node_modules/neo.mjs/src/grid/header","code":{}},"kind":"member","name":"_layout","type":{"names":["String"]},"defaultvalue":"'base'","access":"protected","longname":"_layout","scope":"global","$longname":"_layout","$kind":"property","id":1812,"neoClassName":"Neo.grid.header.Toolbar"},{"comment":"/**\n         * @member {Object} itemDefaults={ntype:'grid-header-button'}\n         * @protected\n         */","meta":{"filename":"Toolbar.mjs","lineno":32,"columnno":8,"path":"/Users/Shared/github/neomjs/neomjs-realworld-example-app/node_modules/neo.mjs/src/grid/header","code":{}},"kind":"member","name":"itemDefaults","type":{"names":["Object"]},"defaultvalue":"{ntype:'grid-header-button'}","access":"protected","longname":"itemDefaults","scope":"global","$longname":"itemDefaults","$kind":"property","id":1813,"neoClassName":"Neo.grid.header.Toolbar"},{"comment":"/**\n         * @member {Object} _vdom\n         * @protected\n         */","meta":{"filename":"Toolbar.mjs","lineno":39,"columnno":8,"path":"/Users/Shared/github/neomjs/neomjs-realworld-example-app/node_modules/neo.mjs/src/grid/header","code":{}},"kind":"member","name":"_vdom","type":{"names":["Object"]},"access":"protected","longname":"_vdom","scope":"global","$longname":"_vdom","$kind":"property","id":1814,"neoClassName":"Neo.grid.header.Toolbar"},{"comment":"/**\n     *\n     * @param {Array} items\n     */","meta":{"range":[1153,1691],"filename":"Toolbar.mjs","lineno":49,"columnno":4,"path":"/Users/Shared/github/neomjs/neomjs-realworld-example-app/node_modules/neo.mjs/src/grid/header","code":{"id":"astnode100054054","name":"Toolbar#createItems","type":"MethodDefinition","paramnames":["items"]},"vars":{"":null}},"params":[{"type":{"names":["Array"]},"name":"items"}],"name":"createItems","longname":"Toolbar#createItems","kind":"function","memberof":"Toolbar","scope":"instance","$longname":"Toolbar#createItems","$kind":"method","id":1815,"neoClassName":"Neo.grid.header.Toolbar"},{"comment":"/**\n     *\n     * @param dock\n     * @returns {String} layoutConfig\n     * @override\n     */","meta":{"range":[1794,1846],"filename":"Toolbar.mjs","lineno":81,"columnno":4,"path":"/Users/Shared/github/neomjs/neomjs-realworld-example-app/node_modules/neo.mjs/src/grid/header","code":{"id":"astnode100054140","name":"Toolbar#getLayoutConfig","type":"MethodDefinition","paramnames":["dock"]},"vars":{"":null}},"params":[{"name":"dock"}],"returns":[{"type":{"names":["String"]},"description":"layoutConfig"}],"override":true,"name":"getLayoutConfig","longname":"Toolbar#getLayoutConfig","kind":"function","memberof":"Toolbar","scope":"instance","$longname":"Toolbar#getLayoutConfig","$kind":"method","id":1816,"neoClassName":"Neo.grid.header.Toolbar"},{"comment":"/**\n     *\n     * @returns {Object}\n     */","meta":{"range":[1900,1953],"filename":"Toolbar.mjs","lineno":89,"columnno":4,"path":"/Users/Shared/github/neomjs/neomjs-realworld-example-app/node_modules/neo.mjs/src/grid/header","code":{"id":"astnode100054147","name":"Toolbar#getVdomRoot","type":"MethodDefinition","paramnames":[]},"vars":{"":null}},"returns":[{"type":{"names":["Object"]}}],"name":"getVdomRoot","longname":"Toolbar#getVdomRoot","kind":"function","memberof":"Toolbar","scope":"instance","params":[],"$longname":"Toolbar#getVdomRoot","$kind":"method","id":1817,"neoClassName":"Neo.grid.header.Toolbar"},{"comment":"/**\n     *\n     * @returns {Object}\n     */","meta":{"range":[2007,2070],"filename":"Toolbar.mjs","lineno":97,"columnno":4,"path":"/Users/Shared/github/neomjs/neomjs-realworld-example-app/node_modules/neo.mjs/src/grid/header","code":{"id":"astnode100054159","name":"Toolbar#getVnodeRoot","type":"MethodDefinition","paramnames":[]},"vars":{"":null}},"returns":[{"type":{"names":["Object"]}}],"name":"getVnodeRoot","longname":"Toolbar#getVnodeRoot","kind":"function","memberof":"Toolbar","scope":"instance","params":[],"$longname":"Toolbar#getVnodeRoot","$kind":"method","id":1818,"neoClassName":"Neo.grid.header.Toolbar"}]}